[
  { "name": "Tissu matelassé",        "category": "Textile",         "compat": "Gambison", "modPA": 0, "malusMod": 0, "effects": "—",              "halfMalus": false, "penIgnore": 0, "res": { "feu": 0, "froid": 0, "foudre": 0, "tr": 0, "per": 0, "con": 0, "magie": 0 } },
  { "name": "Tissu renforcé",         "category": "Textile",         "compat": "Gambison", "modPA": 0, "malusMod": 0, "effects": "—",              "halfMalus": false, "penIgnore": 0, "res": { "feu": 0, "froid": 0, "foudre": 0, "tr": 0, "per": 0, "con": 0, "magie": 0 } },
  { "name": "Soie d’araignée géante", "category": "Textile",         "compat": "Gambison", "modPA": 2, "malusMod": 0, "effects": "—",              "halfMalus": false, "penIgnore": 0, "res": { "feu": 0, "froid": 0, "foudre": 0, "tr": 0, "per": 0, "con": 0, "magie": 0 } },

  { "name": "Cuir",                   "category": "Cuir",            "compat": "Cuir",     "modPA": 0, "malusMod": 0, "effects": "—",              "halfMalus": false, "penIgnore": 0, "res": { "feu": 0, "froid": 0, "foudre": 0, "tr": 0, "per": 0, "con": 0, "magie": 0 } },
  { "name": "Cuir clouté",            "category": "Cuir",            "compat": "Cuir",     "modPA": 1, "malusMod": 1, "effects": "—",              "halfMalus": false, "penIgnore": 0, "res": { "feu": 0, "froid": 0, "foudre": 0, "tr": 0, "per": 0, "con": 0, "magie": 0 } },
  { "name": "Cuir renforcé",          "category": "Cuir",            "compat": "Cuir",     "modPA": 1, "malusMod": 1, "effects": "—",              "halfMalus": false, "penIgnore": 0, "res": { "feu": 0, "froid": 0, "foudre": 0, "tr": 0, "per": 0, "con": 0, "magie": 0 } },
  { "name": "Cuir de wyverne",        "category": "Cuir",            "compat": "Cuir",     "modPA": 2, "malusMod": 0, "effects": "—",              "halfMalus": false, "penIgnore": 0, "res": { "feu": 0, "froid": 0, "foudre": 0, "tr": 0, "per": 0, "con": 0, "magie": 0 } },
  { "name": "Cuir de dragon",         "category": "Cuir",            "compat": "Cuir",     "modPA": 4, "malusMod": 1, "effects": "Feu +2",         "halfMalus": false, "penIgnore": 0, "res": { "feu": 2, "froid": 0, "foudre": 0, "tr": 0, "per": 0, "con": 0, "magie": 0 } },

  { "name": "Fer",                    "category": "MetalFerreux",    "compat": "Métal",    "modPA": 1, "malusMod": 1, "effects": "—",              "halfMalus": false, "penIgnore": 0, "res": { "feu": 0, "froid": 0, "foudre": 0, "tr": 0, "per": 0, "con": 0, "magie": 0 } },
  { "name": "Fer noir",               "category": "MetalFerreux",    "compat": "Métal",    "modPA": 2, "malusMod": 1, "effects": "—",              "halfMalus": false, "penIgnore": 0, "res": { "feu": 0, "froid": 0, "foudre": 0, "tr": 0, "per": 0, "con": 0, "magie": 0 } },
  { "name": "Acier",                  "category": "MetalFerreux",    "compat": "Métal",    "modPA": 2, "malusMod": 2, "effects": "—",              "halfMalus": false, "penIgnore": 0, "res": { "feu": 0, "froid": 0, "foudre": 0, "tr": 0, "per": 0, "con": 0, "magie": 0 } },
  { "name": "Acier renforcé",         "category": "MetalFerreux",    "compat": "Métal",    "modPA": 3, "malusMod": 2, "effects": "—",              "halfMalus": false, "penIgnore": 0, "res": { "feu": 0, "froid": 0, "foudre": 0, "tr": 0, "per": 0, "con": 0, "magie": 0 } },
  { "name": "Acier damassé",          "category": "MetalFerreux",    "compat": "Métal",    "modPA": 3, "malusMod": 2, "effects": "—",              "halfMalus": false, "penIgnore": 0, "res": { "feu": 0, "froid": 0, "foudre": 0, "tr": 0, "per": 0, "con": 0, "magie": 0 } },
  { "name": "Acier noir",             "category": "MetalFerreux",    "compat": "Métal",    "modPA": 6, "malusMod": 4, "effects": "—",              "halfMalus": false, "penIgnore": 0, "res": { "feu": 0, "froid": 0, "foudre": 0, "tr": 0, "per": 0, "con": 0, "magie": 0 } },

  { "name": "Cuivre",                 "category": "MetalNonFerreux", "compat": "Métal",    "modPA": 0, "malusMod": 0, "effects": "—",              "halfMalus": false, "penIgnore": 0, "res": { "feu": 0, "froid": 0, "foudre": 0, "tr": 0, "per": 0, "con": 0, "magie": 0 } },
  { "name": "Bronze",                 "category": "MetalNonFerreux", "compat": "Métal",    "modPA": 0, "malusMod": 1, "effects": "—",              "halfMalus": false, "penIgnore": 0, "res": { "feu": 0, "froid": 0, "foudre": 0, "tr": 0, "per": 0, "con": 0, "magie": 0 } },

  { "name": "Orichalque",             "category": "MetalMythique",   "compat": "Métal",    "modPA": 5, "malusMod": 3, "effects": "Magie +2",       "halfMalus": false, "penIgnore": 0, "res": { "feu": 0, "froid": 0, "foudre": 0, "tr": 0, "per": 0, "con": 0, "magie": 2 } },
  { "name": "Mithril",                "category": "MetalMythique",   "compat": "Métal",    "modPA": 6, "malusMod": 2, "effects": "Malus x0,5",     "halfMalus": true,  "penIgnore": 0, "res": { "feu": 0, "froid": 0, "foudre": 0, "tr": 0, "per": 0, "con": 0, "magie": 0 } },
  { "name": "Adamantium",             "category": "MetalMythique",   "compat": "Métal",    "modPA": 7, "malusMod": 4, "effects": "Ignore 1 pénétration", "halfMalus": false, "penIgnore": 1, "res": { "feu": 0, "froid": 0, "foudre": 0, "tr": 0, "per": 0, "con": 0, "magie": 0 } },

  { "name": "Chitine géante",         "category": "OrganiqueRigide", "compat": "Métal",    "modPA": 3, "malusMod": 2, "effects": "—",              "halfMalus": false, "penIgnore": 0, "res": { "feu": 0, "froid": 0, "foudre": 0, "tr": 0, "per": 0, "con": 0, "magie": 0 } },
  { "name": "Écaille de wyverne",     "category": "OrganiqueRigide", "compat": "Métal",    "modPA": 3, "malusMod": 1, "effects": "—",              "halfMalus": false, "penIgnore": 0, "res": { "feu": 1, "froid": 0, "foudre": 0, "tr": 0, "per": 0, "con": 0, "magie": 0 } },
  { "name": "Osselet runique",        "category": "OrganiqueRigide", "compat": "Métal",    "modPA": 3, "malusMod": 2, "effects": "Magie +1",       "halfMalus": false, "penIgnore": 0, "res": { "feu": 0, "froid": 0, "foudre": 0, "tr": 0, "per": 0, "con": 0, "magie": 1 } },

  { "name": "Bois de fer",            "category": "Bois",            "compat": "Métal",    "modPA": 1, "malusMod": 1, "effects": "—",              "halfMalus": false, "penIgnore": 0, "res": { "feu": 0, "froid": 0, "foudre": 0, "tr": 0, "per": 0, "con": 0, "magie": 0 } },
  { "name": "Bois dur",               "category": "Bois",            "compat": "Métal",    "modPA": 1, "malusMod": 1, "effects": "—",              "halfMalus": false, "penIgnore": 0, "res": { "feu": 0, "froid": 0, "foudre": 0, "tr": 0, "per": 0, "con": 0, "magie": 0 } },

  { "name": "Verre trempé",           "category": "MineralVerre",    "compat": "Métal",    "modPA": 2, "malusMod": 1, "effects": "—",              "halfMalus": false, "penIgnore": 0, "res": { "feu": 0, "froid": 0, "foudre": 0, "tr": 0, "per": 0, "con": 0, "magie": 0 } },
  { "name": "Ébonite",                "category": "ResineDure",      "compat": "Métal",    "modPA": 3, "malusMod": 2, "effects": "Foudre +1",      "halfMalus": false, "penIgnore": 0, "res": { "feu": 0, "froid": 0, "foudre": 1, "tr": 0, "per": 0, "con": 0, "magie": 0 } }
]
